speccheck/__init__.py
speccheck/cli.py
speccheck/collect.py
speccheck/criteria.py
speccheck/main.py
speccheck/report.py
speccheck/update_criteria.py
speccheck/util.py
speccheck/modules/__init__.py
speccheck/modules/ariba.py
speccheck/modules/checkm.py
speccheck/modules/depth.py
speccheck/modules/quast.py
speccheck/modules/speciator.py
speccheck/modules/sylph.py
speccheck/plot_modules/plot_ariba.py
speccheck/plot_modules/plot_checkm.py
speccheck/plot_modules/plot_quast.py
speccheck/plot_modules/plot_speciator.py
speccheck/plot_modules/plot_sylph.py
speccheck_qc-1.2.0.dist-info/licenses/LICENSE
speccheck_qc-1.2.0.dist-info/METADATA
speccheck_qc-1.2.0.dist-info/WHEEL
speccheck_qc-1.2.0.dist-info/entry_points.txt
speccheck_qc-1.2.0.dist-info/top_level.txt
speccheck_qc-1.2.0.dist-info/RECORD
