Metadata-Version: 2.4
Name: speccheck-qc
Version: 1.2.0
Summary: A bioinformatics software focused on quality control based on species criteria
Home-page: https://github.com/happykhan/speccheck
Author: Nabil-Fareed Alikhan
Author-email: Nabil-Fareed Alikhan <nabil@happykhan.com>
Maintainer-email: Nabil-Fareed Alikhan <nabil@happykhan.com>
License: GPLv3
Project-URL: Homepage, https://github.com/happykhan/speccheck
Project-URL: Documentation, https://github.com/happykhan/speccheck
Project-URL: Repository, https://github.com/happykhan/speccheck
Project-URL: Bug Tracker, https://github.com/happykhan/speccheck/issues
Keywords: genomics,qc,bioinformatics,quality-control,genomic-analysis
Classifier: Development Status :: 4 - Beta
Classifier: Intended Audience :: Science/Research
Classifier: License :: OSI Approved :: GNU General Public License v3 (GPLv3)
Classifier: Operating System :: OS Independent
Classifier: Programming Language :: Python :: 3
Classifier: Programming Language :: Python :: 3.10
Classifier: Programming Language :: Python :: 3.11
Classifier: Programming Language :: Python :: 3.12
Classifier: Topic :: Scientific/Engineering :: Bio-Informatics
Requires-Python: >=3.10
License-File: LICENSE
Requires-Dist: rich>=13.0.0
Requires-Dist: jinja2>=3.0.0
Requires-Dist: pandas>=2.0.0
Requires-Dist: requests>=2.28.0
Requires-Dist: plotly>=5.0.0
Requires-Dist: typer>=0.9.0
Provides-Extra: dev
Requires-Dist: pytest>=7.0.0; extra == "dev"
Requires-Dist: pytest-cov>=4.0.0; extra == "dev"
Requires-Dist: coverage>=7.0.0; extra == "dev"
Requires-Dist: pylint>=2.15.0; extra == "dev"
Requires-Dist: black>=23.0.0; extra == "dev"
Requires-Dist: isort>=5.12.0; extra == "dev"
Requires-Dist: ruff>=0.1.0; extra == "dev"
Requires-Dist: bandit>=1.7.0; extra == "dev"
Requires-Dist: safety>=2.3.0; extra == "dev"
Requires-Dist: pre-commit>=3.0.0; extra == "dev"
Dynamic: author
Dynamic: home-page
Dynamic: license-file
Dynamic: requires-python
